[
 	{ "id": "1AP", "name": "Primary - 1A" },
	{ "id": "1BP", "name": "Primary - 1B" },
	{ "id": "1CP", "name": "Primary - 1C" },
	{ "id": "2AP", "name": "Primary - 2A" },
	{ "id": "2BP", "name": "Primary - 2B" },
	{ "id": "2CP", "name": "Primary - 2C" },
	{ "id": "3AP", "name": "Primary - 3A" },
	{ "id": "3BP", "name": "Primary - 3B" },
	{ "id": "3CP", "name": "Primary - 3C" },
	{ "id": "4AP", "name": "Primary - 4A" },
	{ "id": "4BP", "name": "Primary - 4B" },
	{ "id": "4CP", "name": "Primary - 4C" },
	{ "id": "5AP", "name": "Primary - 5A" },
	{ "id": "5BP", "name": "Primary - 5B" },
	{ "id": "5CP", "name": "Primary - 5C" },
	{ "id": "6AP", "name": "Primary - 6A" },
	{ "id": "6BP", "name": "Primary - 6B" },
	{ "id": "6CP", "name": "Primary - 6C" },
	{ "id": "1AS", "name": "Secondary - 1A" },
	{ "id": "1BS", "name": "Secondary - 1B" },
	{ "id": "1CS", "name": "Secondary - 1C" },
	{ "id": "2AS", "name": "Secondary - 2A" },
	{ "id": "2BS", "name": "Secondary - 2B" },
	{ "id": "2CS", "name": "Secondary - 2C" },
	{ "id": "3AS", "name": "Secondary - 3A" },
	{ "id": "3BS", "name": "Secondary - 3B" },
	{ "id": "3CS", "name": "Secondary - 3C" },
	{ "id": "4AS", "name": "Secondary - 4A" },
	{ "id": "4BS", "name": "Secondary - 4B" },
	{ "id": "4CS", "name": "Secondary - 4C" },
	{ "id": "5AS", "name": "Secondary - 5A" },
	{ "id": "5BS", "name": "Secondary - 5B" },
	{ "id": "5CS", "name": "Secondary - 5C" }
]